docs/Makefile
docs/conf.py
docs/index.rst
gqlclient/__init__.py
gqlclient/_version.py
gqlclient/async_client.py
gqlclient/base.py
gqlclient/basemodel_utils.py
gqlclient/client.py
gqlclient/exceptions.py
gqlclient/null.py
gqlclient/request_wrap.py
gqlclient/response_encoders.py
gqlclient/tests/__init__.py
gqlclient/tests/test_async_client.py
gqlclient/tests/test_basemodel_utils_1.py
gqlclient/tests/test_basemodel_utils_2.py
gqlclient/tests/test_graphql_base.py
gqlclient/tests/test_graphql_client.py
gqlclient/tests/test_null.py
gqlclient/tests/test_request_wrap.py
gqlclient/tests/test_response_encoders.py
gqlclient-2.0.0.dist-info/licenses/LICENSE
gqlclient-2.0.0.dist-info/METADATA
gqlclient-2.0.0.dist-info/WHEEL
gqlclient-2.0.0.dist-info/top_level.txt
gqlclient-2.0.0.dist-info/RECORD
