Metadata-Version: 2.4
Name: gqlclient
Version: 2.0.0
Summary: Client library for making graphql calls.
Author-email: NSO / AURA <dkistdc@nso.edu>
License: MIT
Project-URL: repository, https://bitbucket.org/dkistdc/graphql_client/src/master/
Classifier: License :: OSI Approved :: MIT License
Classifier: Programming Language :: Python :: 3
Classifier: Programming Language :: Python :: 3.10
Classifier: Programming Language :: Python :: 3.11
Classifier: Programming Language :: Python :: 3.12
Classifier: Programming Language :: Python :: 3.13
Requires-Python: >=3.10
License-File: LICENSE
Requires-Dist: requests>2.27.0
Requires-Dist: pydantic>=2.4
Requires-Dist: typing-extensions>=4.5; python_version < "3.13"
Provides-Extra: async
Requires-Dist: aiohttp; extra == "async"
Provides-Extra: test
Requires-Dist: tox>=4; extra == "test"
Requires-Dist: pytest; extra == "test"
Requires-Dist: pytest-cov; extra == "test"
Requires-Dist: aiohttp; extra == "test"
Dynamic: license-file
